{
  "type": "extradelight:oven",
  "container": {
    "count": 1,
    "id": "extradelight:sheet"
  },
  "cookingtime": 800,
  "experience": 1.0,
  "ingredients": [
    {
      "item": "minecraft:apple"
    },
    {
      "item": "minecraft:apple"
    },
    {
      "item": "minecraft:apple"
    },
    {
      "item": "minecraft:apple"
    },
    {
      "item": "minecraft:apple"
    },
    {
      "item": "minecraft:apple"
    },
    {
      "item": "minecraft:apple"
    },
    {
      "item": "minecraft:apple"
    }
  ],
  "result": {
    "count": 8,
    "id": "extradelight:roasted_apple"
  }
}